fhir_questionaire_renderer/__init__.py
fhir_questionaire_renderer/component.py
fhir_questionaire_renderer/frontend/.eslintrc.cjs
fhir_questionaire_renderer/frontend/.gitignore
fhir_questionaire_renderer/frontend/dist/assets/index-Dz9LhFgm.js
fhir_questionaire_renderer/frontend/dist/index.html
fhir_questionaire_renderer/frontend/dist/vite.svg
fhir_questionaire_renderer/frontend/index.html
fhir_questionaire_renderer/frontend/package.json
fhir_questionaire_renderer/frontend/public/vite.svg
fhir_questionaire_renderer/frontend/README.md
fhir_questionaire_renderer/frontend/src/assets/react.svg
fhir_questionaire_renderer/frontend/src/FHIRQuestionaireRenderer.tsx
fhir_questionaire_renderer/frontend/src/main.tsx
fhir_questionaire_renderer/frontend/src/vite-env.d.ts
fhir_questionaire_renderer/frontend/tsconfig.json
fhir_questionaire_renderer/frontend/tsconfig.node.json
fhir_questionaire_renderer/frontend/vite.config.ts
fhir_questionaire_renderer/frontend/yarn.lock
fhir_questionaire_renderer-0.1.13.dist-info/METADATA
fhir_questionaire_renderer-0.1.13.dist-info/WHEEL
fhir_questionaire_renderer-0.1.13.dist-info/RECORD
