Metadata-Version: 2.1
Name: fhir-questionaire-renderer
Version: 0.1.13
Summary: 
Author: Axel Vanraes
Author-email: axel.vanraes@tiro.health
Requires-Python: >=3.11,<4.0
Classifier: Programming Language :: Python :: 3
Classifier: Programming Language :: Python :: 3.11
Classifier: Programming Language :: Python :: 3.12
Requires-Dist: streamlit (>=1.31.1,<2.0.0)
